migratron/VERSION
migratron/__init__.py
migratron/consts.py
migratron/main.py
migratron/parsers.py
migratron/command/__init__.py
migratron/command/base.py
migratron/command/cleanup.py
migratron/command/initialize.py
migratron/command/run_migration.py
tests/__init__.py
tests/test_parsers.py
tests/commands/__init__.py
tests/commands/helper.py
tests/commands/test_base.py
tests/commands/test_cleanup.py
tests/commands/test_initialize.py
tests/commands/test_integration.py
tests/commands/test_run_migration.py
migratron-2.2.0.dist-info/LICENSE
migratron-2.2.0.dist-info/METADATA
migratron-2.2.0.dist-info/WHEEL
migratron-2.2.0.dist-info/entry_points.txt
migratron-2.2.0.dist-info/top_level.txt
migratron-2.2.0.dist-info/RECORD
